nanologic/Variable.py
nanologic/__init__.py
nanologic/operations.py
nanologic/util.py
nanologic-0.1.4.dist-info/METADATA
nanologic-0.1.4.dist-info/WHEEL
nanologic-0.1.4.dist-info/licenses/LICENSE
nanologic-0.1.4.dist-info/RECORD
