Metadata-Version: 2.1
Name: nanologic
Version: 0.1.4
Summary: Simple package for simple logical operations
Project-URL: Homepage, https://github.com/alipheesa/nanologic
Project-URL: Bug Tracker, https://github.com/alipheesa/nanologic/issues
Author-email: Alexander Isaychikov <alipheesa@gmail.com>
License-File: LICENSE
Classifier: License :: OSI Approved :: MIT License
Classifier: Operating System :: OS Independent
Classifier: Programming Language :: Python :: 3
Requires-Python: >=3.7
